marvel/__init__.py
marvel/base.py
marvel/endpoint_manager.py
marvel/exceptions.py
marvel/marvel.py
marvel/requester.py
marvel/modules/__init__.py
marvel/modules/base_module.py
marvel/modules/characters.py
marvel/modules/comics.py
marvel/modules/creators.py
marvel/modules/events.py
marvel/modules/series.py
marvel/modules/stories.py
marvel-0.1.0.dist-info/LICENSE.rst
marvel-0.1.0.dist-info/METADATA
marvel-0.1.0.dist-info/WHEEL
marvel-0.1.0.dist-info/top_level.txt
marvel-0.1.0.dist-info/RECORD
