Metadata-Version: 1.1
Name: marvel
Version: 0.1.0
Summary: An API Wrapper For Marvel API: https://developer.marvel.com
Home-page: https://github.com/wrap-away/Marvel
Author: Wrap-Away
Author-email: wrap_away@gmail.com
License: MIT
Keywords: marvel marvel-api spiderman marvel-wrapper marvel-sdk marvel-python
Platform: UNKNOWN
Classifier: Development Status :: 3 - Alpha
Classifier: Environment :: Web Environment
Classifier: Operating System :: OS Independent
Classifier: Intended Audience :: Developers
Classifier: Topic :: Software Development :: Build Tools
Classifier: License :: OSI Approved :: MIT License
Classifier: Programming Language :: Python
Classifier: Programming Language :: Python :: 3
Classifier: Programming Language :: Python :: 3.3
Classifier: Programming Language :: Python :: 3.4
Classifier: Programming Language :: Python :: 3.5
